__init__.py
fastapi_resource_server.py
fastapi_resource_server-0.1.2.dist-info/LICENSE
fastapi_resource_server-0.1.2.dist-info/WHEEL
fastapi_resource_server-0.1.2.dist-info/METADATA
fastapi_resource_server-0.1.2.dist-info/RECORD
