Metadata-Version: 2.1
Name: fastapi-resource-server
Version: 0.1.2
Summary: Build resource servers with FastAPI
Home-page: https://github.com/livioribeiro/fastapi-resource-server
License: MIT
Keywords: fastapi,authentication,oidc,openidconnect
Author: Livio Ribeiro
Author-email: livioribeiro@outlook.com
Requires-Python: >=3.6.2,<4.0.0
Classifier: Development Status :: 4 - Beta
Classifier: Environment :: Web Environment
Classifier: Intended Audience :: Developers
Classifier: Intended Audience :: Information Technology
Classifier: License :: OSI Approved :: MIT License
Classifier: Programming Language :: Python :: 3
Classifier: Programming Language :: Python :: 3 :: Only
Classifier: Programming Language :: Python :: 3.6
Classifier: Programming Language :: Python :: 3.7
Classifier: Programming Language :: Python :: 3.8
Classifier: Programming Language :: Python :: 3.9
Classifier: Topic :: Internet
Classifier: Topic :: Internet :: WWW/HTTP
Classifier: Topic :: Internet :: WWW/HTTP :: HTTP Servers
Classifier: Topic :: Software Development :: Libraries
Classifier: Topic :: Software Development :: Libraries :: Application Frameworks
Classifier: Topic :: Software Development :: Libraries :: Python Modules
Requires-Dist: fastapi (>=0,<1)
Requires-Dist: python-jose (>=3.2,<4.0)
Project-URL: Repository, https://github.com/livioribeiro/fastapi-resource-server
